inserter/__init__.py
inserter/ch_swap_inserter.py
inserter/swap_inserter.py
inserter/vertica_swap_inserter.py
swap_inserter_talenttech_oss-0.0.4.dist-info/LICENSE.txt
swap_inserter_talenttech_oss-0.0.4.dist-info/METADATA
swap_inserter_talenttech_oss-0.0.4.dist-info/WHEEL
swap_inserter_talenttech_oss-0.0.4.dist-info/top_level.txt
swap_inserter_talenttech_oss-0.0.4.dist-info/RECORD
