Metadata-Version: 2.1
Name: swap-inserter-talenttech-oss
Version: 0.0.4
Summary: Custom insert for script in vertica/ch
Home-page: https://github.com/severgroup-tt/topmind-commons/tree/master/py/swap-inserter
Author: Dmitry Utiralov
Author-email: d.utiralov@talenttech.ru
License: MIT
Platform: UNKNOWN
Classifier: Programming Language :: Python :: 3
Classifier: License :: OSI Approved :: MIT License
Classifier: Operating System :: OS Independent
Requires-Python: >=3.6
License-File: LICENSE.txt
Requires-Dist: clickhouse-balanced-talenttech-oss (==0.0.1)
Requires-Dist: vertica-connector-talenttech (==1.2.0)
